palm_rlhf_pytorch/__init__.py
palm_rlhf_pytorch/attention.py
palm_rlhf_pytorch/flowrl.py
palm_rlhf_pytorch/grpo.py
palm_rlhf_pytorch/implicit_process_reward.py
palm_rlhf_pytorch/lora.py
palm_rlhf_pytorch/palm.py
palm_rlhf_pytorch/ppo.py
palm_rlhf_pytorch/reward.py
palm_rlhf_pytorch/utils.py
palm_rlhf_pytorch-0.7.1.dist-info/licenses/LICENSE
palm_rlhf_pytorch-0.7.1.dist-info/METADATA
palm_rlhf_pytorch-0.7.1.dist-info/WHEEL
palm_rlhf_pytorch-0.7.1.dist-info/top_level.txt
palm_rlhf_pytorch-0.7.1.dist-info/RECORD
