Metadata-Version: 2.4
Name: PaLM-rlhf-pytorch
Version: 0.7.1
Summary: PaLM + Reinforcement Learning with Human Feedback - Pytorch
Home-page: https://github.com/lucidrains/PaLM-rlhf-pytorch
Author: Phil Wang
Author-email: lucidrains@gmail.com
License: MIT
Keywords: artificial intelligence,deep learning,transformers,attention mechanism,reinforcement learning,human feedback
Classifier: Development Status :: 4 - Beta
Classifier: Intended Audience :: Developers
Classifier: Topic :: Scientific/Engineering :: Artificial Intelligence
Classifier: License :: OSI Approved :: MIT License
Classifier: Programming Language :: Python :: 3.6
License-File: LICENSE
Requires-Dist: accelerate
Requires-Dist: adam-atan2-pytorch
Requires-Dist: beartype
Requires-Dist: einx>=0.3.0
Requires-Dist: einops>=0.8.0
Requires-Dist: hl-gauss-pytorch>=0.1.19
Requires-Dist: torch>=2.2
Requires-Dist: tqdm
Requires-Dist: x-mlps-pytorch
Dynamic: author
Dynamic: author-email
Dynamic: classifier
Dynamic: description-content-type
Dynamic: home-page
Dynamic: keywords
Dynamic: license
Dynamic: license-file
Dynamic: requires-dist
Dynamic: summary
